{
  "common_searches": {
     [{
      "keyword": "Updated Keyword",
      "category": "Updated Category",
      "score": 65786,
      "psxKeyword": "Dermatologist",
      "pesKeyword": "02-012-008",
      "searchType": "Specialty",
      "icon": "syringe",
      "coverageType": "M",
      "enableMemberRelevancy": true
    },
    {
      "keyword": "New Term",
      "category": "New Category",
      "score": 789,
      "psxKeyword": "Keyword1",
      "pesKeyword": "02-012-008",
      "searchType": "Specialty",
      "icon": "icon1",
      "coverageType": "M",
      "enableMemberRelevancy": true
    }]
  },
  "common_searches_new": {
    [{
      "keyword": "Updated Keyword",
      "category": "Updated Category",
      "score": 65786,
      "psxKeyword": "Dermatologist",
      "pesKeyword": "02-012-008",
      "searchType": "Specialty",
      "icon": "syringe",
      "coverageType": "M",
      "enableMemberRelevancy": true
    },
     {
      "keyword": "New Term",
      "category": "New Category",
      "score": 789,
      "psxKeyword": "Keyword1",
      "pesKeyword": "02-012-008",
      "searchType": "Specialty",
      "icon": "icon1",
      "coverageType": "M",
      "enableMemberRelevancy": true
    }]
  }
}
